{
  "_comment": "Single source of truth: briefKey -> rendered Cloudflare Stream video. Replaces hardcoded streamUids in the HumanDesign app (home.js/blueprint.js/today.js). The acceptance gate (check-video-briefs.mjs) enforces no dead pointers.",
  "streamAccount": "customer-op4b8eq1uv0ciwqy",
  "videos": {
    "daily-transits-guide": {
      "streamUid": "78406f1f1c075526114990c0586d3762",
      "renderedAt": "2026-05-21",
      "lastValidated": "2026-06-17"
    },
    "gate-concept-1": {
      "streamUid": "a82d77cf1283b91b86be9783c4774cb5",
      "capricastUrl": "https://capricast.com/watch/c662d426-2c06-41b8-9780-54fb6add1ecd",
      "renderedAt": "2026-06-17",
      "lastValidated": "2026-06-17",
      "forge": "phoenix",
      "composition": "EnergyBlueprintVideo"
    }
  }
}
